{ 
    "featured":[
        {
            "title":"🍂",
            "description":"Featured Fall Playlist",
            "creator":"Arianna Kamal '23",
            "platform_img":"images/spotify.png",
            "playlist_url":"https://open.spotify.com/playlist/7Emd5MmtCBTeaByTXQD37f?si=-Zw6qU1QTkOAuGCP8wZqug"
        },

    {
        "title":"crunchy leaves",
        "description":"Featured Fall Playlist",
        "creator":"Tyler Tjan '22",
        "platform_img":"images/spotify.png",
        "playlist_url":"https://open.spotify.com/playlist/6vCAnFpWg1xHpII8jlCH8m?si=1cz8wPlSQMeOZT_vOshXWg"

    }

]

}